hydro_topo_features/__init__.py
hydro_topo_features/config.py
hydro_topo_features/pipeline.py
hydro_topo_features/processing/__init__.py
hydro_topo_features/processing/burn_dem.py
hydro_topo_features/processing/derive_products.py
hydro_topo_features/processing/prepare_data.py
hydro_topo_features/visualization/__init__.py
hydro_topo_features/visualization/interactive.py
hydro_topo_features/visualization/static.py
hydro_topo_features-0.1.4.dist-info/METADATA
hydro_topo_features-0.1.4.dist-info/WHEEL
hydro_topo_features-0.1.4.dist-info/top_level.txt
hydro_topo_features-0.1.4.dist-info/RECORD
