Metadata-Version: 2.4
Name: hydro-topo-features
Version: 0.1.4
Summary: Extract hydro-topographic features from DEM and OSM data
Home-page: https://github.com/paulhosch/hydro_topo_features
Author: Paul Hosch
Author-email: paul.hosch@rwth-aachen.de
Project-URL: Documentation, https://hydro-topo-features.readthedocs.io/
Project-URL: Source Code, https://github.com/paulhosch/hydro_topo_features
Project-URL: Bug Tracker, https://github.com/paulhosch/hydro_topo_features/issues
Keywords: dem,hydrology,gis,osm,hand,flood mapping,terrain analysis
Classifier: Development Status :: 4 - Beta
Classifier: Intended Audience :: Science/Research
Classifier: License :: OSI Approved :: MIT License
Classifier: Programming Language :: Python :: 3
Classifier: Programming Language :: Python :: 3.11
Classifier: Topic :: Scientific/Engineering :: GIS
Classifier: Topic :: Scientific/Engineering :: Hydrology
Requires-Python: >=3.11
Requires-Dist: numpy>=1.26.0
Requires-Dist: rasterio>=1.3.8
Requires-Dist: geopandas>=0.14.0
Requires-Dist: pysheds>=0.3.3
Requires-Dist: matplotlib>=3.7.0
Requires-Dist: folium>=0.14.0
Requires-Dist: cartopy>=0.22.0
Requires-Dist: geemap>=0.28.0
Requires-Dist: osmnx>=1.5.0
Requires-Dist: scipy>=1.10.0
Requires-Dist: tqdm>=4.64.0
Requires-Dist: geopy>=2.4.0
Provides-Extra: docs
Requires-Dist: sphinx>=4.0.0; extra == "docs"
Requires-Dist: sphinx_rtd_theme>=1.0.0; extra == "docs"
Requires-Dist: sphinx-autodoc-typehints; extra == "docs"
Dynamic: author
Dynamic: author-email
Dynamic: classifier
Dynamic: description
Dynamic: description-content-type
Dynamic: home-page
Dynamic: keywords
Dynamic: project-url
Dynamic: provides-extra
Dynamic: requires-dist
Dynamic: requires-python
Dynamic: summary
